README.md
setup.py
docs/conf.py
docs/index.rst
docs/reference.rst
docs/_static/theme_override.css
tests/__init__.py
tests/test_strains.py
weedmaps/__init__.py
weedmaps/base.py
weedmaps/models.py
weedmaps.egg-info/PKG-INFO
weedmaps.egg-info/SOURCES.txt
weedmaps.egg-info/dependency_links.txt
weedmaps.egg-info/top_level.txt